gesture_app/__init__.py
gesture_app/__version__.py
gesture_app/_utils.py
gesture_app/cli.py
gesture_app/model/__init__.py
gesture_app/model/clean_image.py
gesture_app/model/gesture_prediction.py
gesture_app/model/tf_lite_model.tflite
gesture_app/model/config/__init__.py
gesture_app-0.1.1.dist-info/LICENSE
gesture_app-0.1.1.dist-info/METADATA
gesture_app-0.1.1.dist-info/WHEEL
gesture_app-0.1.1.dist-info/entry_points.txt
gesture_app-0.1.1.dist-info/top_level.txt
gesture_app-0.1.1.dist-info/RECORD
