Metadata-Version: 2.1
Name: gesture-app
Version: 0.1.1
Summary: the hand gesture recognition app
Home-page: https://github.com/vempaliakhil96/hand-detection
Author: Akhil Vempali
Author-email: vempaliakhil96@gmail.com
License: Apache 2.0
Platform: UNKNOWN
Classifier: License :: OSI Approved :: Apache Software License
Classifier: Programming Language :: Python :: 3.6
Classifier: Programming Language :: Python :: 3.7
Requires-Dist: Click (==7.0)
Requires-Dist: opencv-python (==4.1.0.25)
Requires-Dist: tensorflow (==2.0.0)
Requires-Dist: keyboard (==0.13.5)
Requires-Dist: numpy (==1.18.4)
